{
	"info": {
		"_postman_id": "716b5192-023b-4648-9882-6b49f4527936",
		"name": "Saytutention",
		"schema": "https://schema.getpostman.com/json/collection/v2.0.0/collection.json",
		"_exporter_id": "31562857"
	},
	"item": [
		{
			"name": "Advice-ressource",
			"item": [
				{
					"name": "login",
					"request": {
						"method": "GET",
						"header": []
					},
					"response": []
				},
				{
					"name": "Post advice-ressource",
					"event": [
						{
							"listen": "test",
							"script": {
								"exec": [
									"var jsonData = JSON.parse(responseBody);\r",
									"pm.environment.set(\"id\", jsonData.id);"
								],
								"type": "text/javascript"
							}
						}
					],
					"request": {
						"auth": {
							"type": "basic",
							"basic": {
								"password": "fyc2ELY&07z1Q7",
								"username": "adminlocalhost@gmail.com"
							}
						},
						"method": "POST",
						"header": [
							{
								"key": "Content-Type",
								"value": "application/json",
								"type": "text"
							},
							{
								"warning": "This is a duplicate header and will be overridden by the Authorization header generated by Postman.",
								"key": "Authorization",
								"value": "token  eyJhbGciOiJIUzUxMiJ9.eyJzdWIiOiJhZG1pbmxvY2FsaG9zdEBnbWFpbC5jb20iLCJhdXRoIjoiUk9MRV9BRE1JTixST0xFX0JPLFJPTEVfVVNFUiIsImV4cCI6MTcwNTc2ODc4Nn0.ahB3dXyPzyi14qb7c0TWbAF_JBpPDcBS5Nge91kPvbp8lL6qbk8PJ-eTGG_VKj6Y41pd9tsKIzXM0R8RnzftxA",
								"type": "text"
							}
						],
						"body": {
							"mode": "raw",
							"raw": "{\r\n\"createdBy\": \"admin\",\r\n\"createdDate\": \"2023-07-24T14:56:49.626004Z\",\r\n \"lastModifiedBy\": \"750451150\",\r\n \"lastModifiedDate\": \"2023-08-30T17:09:23.837670Z\",\r\n\"title\": \"TestPost\",\r\n\"description\": \"Methode POST pour recuperer un élément supprimer par DELETE\",\r\n\"numberOfRead\": 42,\r\n\"imageUrl\": \"https://file-service.saytutension.baamtuservices.com/files-service/api/download/saytutension/image.jpeg\"\r\n}",
							"options": {
								"raw": {
									"language": "json"
								}
							}
						},
						"url": "{{SaytuTention}}advice"
					},
					"response": []
				},
				{
					"name": "Get advice-ressource count 0",
					"request": {
						"auth": {
							"type": "basic",
							"basic": {
								"password": "fyc2ELY&07z1Q7",
								"username": "adminlocalhost@gmail.com"
							}
						},
						"method": "GET",
						"header": [
							{
								"key": "Content-Type",
								"value": "application/json",
								"type": "text"
							}
						],
						"url": "{{SaytuTention}}advice/count"
					},
					"response": []
				},
				{
					"name": "Get advice-ressource (id)",
					"protocolProfileBehavior": {
						"followAuthorizationHeader": false
					},
					"request": {
						"auth": {
							"type": "basic",
							"basic": {
								"password": "fyc2ELY&07z1Q7",
								"username": "adminlocalhost@gmail.com"
							}
						},
						"method": "GET",
						"header": [
							{
								"key": "Content-Type",
								"value": "application/vnd.api+json",
								"type": "text"
							},
							{
								"warning": "This is a duplicate header and will be overridden by the Authorization header generated by Postman.",
								"key": "Authorization",
								"value": "token  eyJhbGciOiJIUzUxMiJ9.eyJzdWIiOiJhZG1pbmxvY2FsaG9zdEBnbWFpbC5jb20iLCJhdXRoIjoiUk9MRV9BRE1JTixST0xFX0JPLFJPTEVfVVNFUiIsImV4cCI6MTcwNTc2ODc4Nn0.ahB3dXyPzyi14qb7c0TWbAF_JBpPDcBS5Nge91kPvbp8lL6qbk8PJ-eTGG_VKj6Y41pd9tsKIzXM0R8RnzftxA",
								"type": "text"
							}
						],
						"url": "{{SaytuTention}}advice/{{id}}"
					},
					"response": []
				},
				{
					"name": "Path advice-ressource (id)",
					"request": {
						"auth": {
							"type": "basic",
							"basic": {
								"password": "fyc2ELY&07z1Q7",
								"username": "adminlocalhost@gmail.com"
							}
						},
						"method": "PATCH",
						"header": [
							{
								"key": "Content-Type",
								"value": "application/json",
								"type": "text"
							}
						],
						"body": {
							"mode": "raw",
							"raw": "{\r\n    \"createdBy\": \"admin\",\r\n    \"createdDate\": \"2023-22-13T11:05:16.187683Z\",\r\n    \"lastModifiedBy\": \"773451150\",\r\n    \"lastModifiedDate\": \"2023-08-30T15:37:24.200410Z\",\r\n    \"id\": 21501,\r\n   \"title\": \"HTA\",\r\n    \"description\": \"Reduire l'HTA \",\r\n    \"numberOfRead\": 4500\r\n}",
							"options": {
								"raw": {
									"language": "json"
								}
							}
						},
						"url": "{{SaytuTention}}advice/{{id}}"
					},
					"response": []
				},
				{
					"name": "Get advice-ressource count 1",
					"request": {
						"auth": {
							"type": "basic",
							"basic": {
								"password": "fyc2ELY&07z1Q7",
								"username": "adminlocalhost@gmail.com"
							}
						},
						"method": "GET",
						"header": [
							{
								"key": "Content-Type",
								"value": "application/json",
								"type": "text"
							}
						],
						"url": "{{SaytuTention}}advice/count"
					},
					"response": []
				},
				{
					"name": "Delete advice-ressource (id)",
					"request": {
						"auth": {
							"type": "basic",
							"basic": {
								"password": "fyc2ELY&07z1Q7",
								"username": "adminlocalhost@gmail.com"
							}
						},
						"method": "DELETE",
						"header": [
							{
								"key": "Content-Type",
								"value": "application/vnd.api+json",
								"type": "text"
							},
							{
								"warning": "This is a duplicate header and will be overridden by the Authorization header generated by Postman.",
								"key": "Authorization",
								"value": "token  eyJhbGciOiJIUzUxMiJ9.eyJzdWIiOiJhZG1pbmxvY2FsaG9zdEBnbWFpbC5jb20iLCJhdXRoIjoiUk9MRV9BRE1JTixST0xFX0JPLFJPTEVfVVNFUiIsImV4cCI6MTcwNTc2ODc4Nn0.ahB3dXyPzyi14qb7c0TWbAF_JBpPDcBS5Nge91kPvbp8lL6qbk8PJ-eTGG_VKj6Y41pd9tsKIzXM0R8RnzftxA",
								"type": "text"
							}
						],
						"url": "{{SaytuTention}}advice/{{id}}"
					},
					"response": []
				},
				{
					"name": "Get advice-ressource count 2",
					"request": {
						"auth": {
							"type": "basic",
							"basic": {
								"password": "fyc2ELY&07z1Q7",
								"username": "adminlocalhost@gmail.com"
							}
						},
						"method": "GET",
						"header": [
							{
								"key": "Content-Type",
								"value": "application/json",
								"type": "text"
							}
						],
						"url": "{{SaytuTention}}advice/count"
					},
					"response": []
				},
				{
					"name": "get advice-ressource",
					"request": {
						"auth": {
							"type": "basic",
							"basic": {
								"password": "fyc2ELY&07z1Q7",
								"username": "adminlocalhost@gmail.com"
							}
						},
						"method": "GET",
						"header": [],
						"url": {
							"raw": "{{SaytuTention}}advice?page=0&size=30&search=false ",
							"host": [
								"{{SaytuTention}}advice"
							],
							"query": [
								{
									"key": "page",
									"value": "0"
								},
								{
									"key": "size",
									"value": "30"
								},
								{
									"key": "search",
									"value": "false "
								}
							]
						}
					},
					"response": []
				},
				{
					"name": "Put advice-ressource (id)",
					"request": {
						"auth": {
							"type": "basic",
							"basic": {
								"password": "fyc2ELY&07z1Q7",
								"username": "adminlocalhost@gmail.com"
							}
						},
						"method": "PUT",
						"header": [
							{
								"key": "Content-Type",
								"value": "application/vnd.api+json",
								"type": "text"
							},
							{
								"warning": "This is a duplicate header and will be overridden by the Authorization header generated by Postman.",
								"key": "Authorization",
								"value": "token  eyJhbGciOiJIUzUxMiJ9.eyJzdWIiOiJhZG1pbmxvY2FsaG9zdEBnbWFpbC5jb20iLCJhdXRoIjoiUk9MRV9BRE1JTixST0xFX0JPLFJPTEVfVVNFUiIsImV4cCI6MTcwNTc2ODc4Nn0.ahB3dXyPzyi14qb7c0TWbAF_JBpPDcBS5Nge91kPvbp8lL6qbk8PJ-eTGG_VKj6Y41pd9tsKIzXM0R8RnzftxA",
								"type": "text"
							}
						],
						"body": {
							"mode": "raw",
							"raw": "{\r\n    \"createdBy\": \"admin\",\r\n    \"createdDate\": \"2023-07-13T11:05:16.187683Z\",\r\n    \"lastModifiedBy\": \"773451150\",\r\n    \"lastModifiedDate\": \"2023-08-30T15:37:24.200410Z\",\r\n    \"id\": {{id}},\r\n   \"title\": \"HTA N0\",\r\n    \"description\": \"Reduire l'HTA de 20% d'ici fin 2024\",\r\n    \"numberOfRead\": 4,\r\n    \"imageUrl\": \"https://file-service.saytutension.baamtuservices.com/files-service/api/download/saytutension/image.jpeg\"\r\n}\r\n",
							"options": {
								"raw": {
									"language": "json"
								}
							}
						},
						"url": "{{SaytuTention}}advice/{{id}}"
					},
					"response": []
				}
			],
			"auth": {
				"type": "basic",
				"basic": {
					"password": "fyc2ELY&07z1Q7\t",
					"username": "adminlocalhost@gmail.com"
				}
			},
			"event": [
				{
					"listen": "prerequest",
					"script": {
						"type": "text/javascript",
						"exec": [
							""
						]
					}
				},
				{
					"listen": "test",
					"script": {
						"type": "text/javascript",
						"exec": [
							""
						]
					}
				}
			]
		}
	]
}